AUTHORS.rst
CONTRIBUTING.rst
HISTORY.rst
LICENSE
MANIFEST.in
README.rst
setup.cfg
setup.py
calendars/__init__.py
calendars/admin.py
calendars/models.py
calendars/parsing.py
calendars/management/__init__.py
calendars/management/commands/__init__.py
calendars/management/commands/read_calendars.py
calendars/migrations/0001_initial.py
calendars/migrations/__init__.py
connector_calendars.egg-info/PKG-INFO
connector_calendars.egg-info/SOURCES.txt
connector_calendars.egg-info/dependency_links.txt
connector_calendars.egg-info/not-zip-safe
connector_calendars.egg-info/requires.txt
connector_calendars.egg-info/top_level.txt